gempy_viewer/__init__.py
gempy_viewer/_version.py
gempy_viewer/optional_dependencies.py
gempy_viewer/API/__init__.py
gempy_viewer/API/_plot_2d_API.py
gempy_viewer/API/_plot_2d_sections_api.py
gempy_viewer/API/_plot_3d_API.py
gempy_viewer/API/_plot_LiquidEarth.py
gempy_viewer/API/_plot_others.py
gempy_viewer/DEP/__init__.py
gempy_viewer/DEP/_plot.py
gempy_viewer/DEP/_visualization_2d.py
gempy_viewer/DEP/decorators.py
gempy_viewer/DEP/visualization_3d.py
gempy_viewer/core/__init__.py
gempy_viewer/core/data_to_show.py
gempy_viewer/core/plotting_2d_options.py
gempy_viewer/core/scalar_data_type.py
gempy_viewer/core/section_data_2d.py
gempy_viewer/core/slicer_data.py
gempy_viewer/modules/__init__.py
gempy_viewer/modules/plot_2d/__init__.py
gempy_viewer/modules/plot_2d/drawer_contours_2d.py
gempy_viewer/modules/plot_2d/drawer_input_2d.py
gempy_viewer/modules/plot_2d/drawer_regular_grid_2d.py
gempy_viewer/modules/plot_2d/drawer_scalar_field_2d.py
gempy_viewer/modules/plot_2d/drawer_topography_2d.py
gempy_viewer/modules/plot_2d/drawer_traces_2d.py
gempy_viewer/modules/plot_2d/helpers.py
gempy_viewer/modules/plot_2d/multi_axis_manager.py
gempy_viewer/modules/plot_2d/plot_2d_utils.py
gempy_viewer/modules/plot_2d/plot_utils_DEP.py
gempy_viewer/modules/plot_2d/visualization_2d.py
gempy_viewer/modules/plot_3d/__init__.py
gempy_viewer/modules/plot_3d/_vista.py
gempy_viewer/modules/plot_3d/drawer_input_3d.py
gempy_viewer/modules/plot_3d/drawer_structured_grid_3d.py
gempy_viewer/modules/plot_3d/drawer_surfaces_3d.py
gempy_viewer/modules/plot_3d/drawer_topography_3d.py
gempy_viewer/modules/plot_3d/plot_3d_utils.py
gempy_viewer/modules/plot_3d/vista.py
gempy_viewer/modules/plot_3d/vista_qt.py
gempy_viewer-2025.1.6.dist-info/licenses/AUTHORS.rst
gempy_viewer-2025.1.6.dist-info/licenses/LICENSE
tests/__init__.py
tests/conftest.py
tests/test_installation.py
tests/util_tests.py
tests/test_plotting/__init__.py
tests/test_plotting/test_plot_2d.py
tests/test_plotting/test_plot_3d.py
tests/test_private/__init__.py
tests/test_private/test_terranigma/__init__.py
gempy_viewer-2025.1.6.dist-info/METADATA
gempy_viewer-2025.1.6.dist-info/WHEEL
gempy_viewer-2025.1.6.dist-info/top_level.txt
gempy_viewer-2025.1.6.dist-info/RECORD
