Metadata-Version: 2.4
Name: gempy_viewer
Version: 2025.1.6
Summary: Viewer for the geological modeling package GemPy
Home-page: 
Author: Miguel de la Varga
Author-email: miguel@terranigma-solutions.com
License: EUPL
Classifier: Development Status :: 3 - Alpha
Classifier: Intended Audience :: Science/Research
Classifier: Topic :: Scientific/Engineering :: Visualization
Classifier: Topic :: Scientific/Engineering :: GIS
Classifier: Programming Language :: Python :: 3.10
Requires-Python: >=3.10
License-File: LICENSE
License-File: AUTHORS.rst
Requires-Dist: matplotlib
Requires-Dist: numpy
Provides-Extra: opt
Requires-Dist: matplotlib; extra == "opt"
Requires-Dist: numpy; extra == "opt"
Requires-Dist: pyvista; extra == "opt"
Requires-Dist: scikit-image; extra == "opt"
Requires-Dist: scipy; extra == "opt"
Requires-Dist: pooch; extra == "opt"
Requires-Dist: pandas; extra == "opt"
Requires-Dist: liquid-earth-sdk; extra == "opt"
Provides-Extra: dev
Requires-Dist: matplotlib; extra == "dev"
Requires-Dist: numpy; extra == "dev"
Requires-Dist: pyvista; extra == "dev"
Requires-Dist: scikit-image; extra == "dev"
Requires-Dist: scipy; extra == "dev"
Requires-Dist: pooch; extra == "dev"
Requires-Dist: pandas; extra == "dev"
Requires-Dist: liquid-earth-sdk; extra == "dev"
Requires-Dist: pytest; extra == "dev"
Requires-Dist: gempy; extra == "dev"
Requires-Dist: imagehash; extra == "dev"
Requires-Dist: pillow; extra == "dev"
Requires-Dist: pydantic; extra == "dev"
Requires-Dist: gempy<2025.3.0,>=2025.2.0dev0; extra == "dev"
Dynamic: author
Dynamic: author-email
Dynamic: classifier
Dynamic: license
Dynamic: license-file
Dynamic: provides-extra
Dynamic: requires-dist
Dynamic: requires-python
Dynamic: summary
